plcdoc/__init__.py
plcdoc/__version__.py
plcdoc/auto_directives.py
plcdoc/common.py
plcdoc/directives.py
plcdoc/documenters.py
plcdoc/domain.py
plcdoc/extension.py
plcdoc/interpreter.py
plcdoc/roles.py
plcdoc/st_declaration.tx
plcdoc-0.0.1.dist-info/METADATA
plcdoc-0.0.1.dist-info/WHEEL
plcdoc-0.0.1.dist-info/top_level.txt
plcdoc-0.0.1.dist-info/RECORD
