Metadata-Version: 2.1
Name: plcdoc
Version: 0.0.1
Summary: A tool to create PLC documentation for Sphinx
Author-email: Robert Roos <robert.soor@gmail.com>
License: BSD-3-Clause
Project-URL: Homepage, https://github.com/DEMCON/plcdoc
Project-URL: Bug Tracker, https://github.com/DEMCON/plcdoc/issues
Project-URL: Documentation, https://plc-doc.readthedocs.io/latest/
Classifier: Programming Language :: Python :: 3
Classifier: License :: OSI Approved :: MIT License
Classifier: Operating System :: OS Independent
Requires-Python: >=3.9
Requires-Dist: sphinx <7.0,>=5.0
Requires-Dist: textX >=3.0
Provides-Extra: doc
Requires-Dist: sphinx-rtd-theme >=1.4 ; extra == 'doc'
Provides-Extra: test
Requires-Dist: black >=23.0 ; extra == 'test'
Requires-Dist: pytest >=6.0 ; extra == 'test'
Requires-Dist: pytest-cov >=4.0 ; extra == 'test'
Requires-Dist: flake8 >=6.0 ; extra == 'test'
Requires-Dist: flake8-bugbear >=23.0 ; extra == 'test'
